{
    "Exposes": [
        {
            "Address": "0x8",
            "Class": "METemp",
            "Name": "PCH_Temp",
            "PowerState": "On",
            "Thresholds": [
                {
                    "Direction": "greater than",
                    "Name": "upper critical",
                    "Severity": 1,
                    "Value": 90
                }
            ],
            "Type": "IpmbSensor"
        },
        {
            "Address": "0x30",
            "Bus": 0,
            "CpuID": 1,
            "Name": "CPU0 Temp",
            "Labels": [
                {
                    "Die" : "CPU0_Temp",
                    "DIMM_A1" : "CPU0_MC0_DIMM_A",
                    "DIMM_B1" : "CPU0_MC0_DIMM_B",
                    "DIMM_C1" : "CPU0_MC0_DIMM_C",
                    "DIMM_D1" : "CPU0_MC1_DIMM_D",
                    "DIMM_E1" : "CPU0_MC1_DIMM_E",
                    "DIMM_F1" : "CPU0_MC1_DIMM_F",
                    "Tjmax" : "CPU0_DTS_Margin"
                }
            ],
            "Thresholds": [
                {
                    "Direction": "greater than",
                    "Label": "DIMM_A1",
                    "Name": "upper critical",
                    "Severity": 1,
                    "Value": 85
                },
                {
                    "Direction": "greater than",
                    "Label": "DIMM_B1",
                    "Name": "upper critical",
                    "Severity": 1,
                    "Value": 85
                },
                {
                    "Direction": "greater than",
                    "Label": "DIMM_C1",
                    "Name": "upper critical",
                    "Severity": 1,
                    "Value": 85
                },
                {
                    "Direction": "greater than",
                    "Label": "DIMM_D1",
                    "Name": "upper critical",
                    "Severity": 1,
                    "Value": 85
                },
                {
                    "Direction": "greater than",
                    "Label": "DIMM_E1",
                    "Name": "upper critical",
                    "Severity": 1,
                    "Value": 85
                },
                {
                    "Direction": "greater than",
                    "Label": "DIMM_F1",
                    "Name": "upper critical",
                    "Severity": 1,
                    "Value": 85
                },
                {
                    "Direction": "greater than",
                    "Label": "Die",
                    "Name": "upper critical",
                    "Severity": 1,
                    "Value": 95
                }
            ],
            "Type": "XeonCPU"
        },
        {
            "Address": "0x31",
            "Bus": 0,
            "CpuID": 2,
            "Name": "CPU1 Temp",
            "Labels": [
                {
                    "Die" : "CPU1_Temp",
                    "DIMM_A1" : "CPU1_MC0_DIMM_A",
                    "DIMM_B1" : "CPU1_MC0_DIMM_B",
                    "DIMM_C1" : "CPU1_MC0_DIMM_C",
                    "DIMM_D1" : "CPU1_MC1_DIMM_D",
                    "DIMM_E1" : "CPU1_MC1_DIMM_E",
                    "DIMM_F1" : "CPU1_MC1_DIMM_F",
                    "Tjmax" : "CPU1_DTS_Margin"
                }
            ],
            "Thresholds": [
                {
                    "Direction": "greater than",
                    "Label": "DIMM_A1",
                    "Name": "upper critical",
                    "Severity": 1,
                    "Value": 85
                },
                {
                    "Direction": "greater than",
                    "Label": "DIMM_B1",
                    "Name": "upper critical",
                    "Severity": 1,
                    "Value": 85
                },
                {
                    "Direction": "greater than",
                    "Label": "DIMM_C1",
                    "Name": "upper critical",
                    "Severity": 1,
                    "Value": 85
                },
                {
                    "Direction": "greater than",
                    "Label": "DIMM_D1",
                    "Name": "upper critical",
                    "Severity": 1,
                    "Value": 85
                },
                {
                    "Direction": "greater than",
                    "Label": "DIMM_E1",
                    "Name": "upper critical",
                    "Severity": 1,
                    "Value": 85
                },
                {
                    "Direction": "greater than",
                    "Label": "DIMM_F1",
                    "Name": "upper critical",
                    "Severity": 1,
                    "Value": 85
                },
                {
                    "Direction": "greater than",
                    "Label": "Die",
                    "Name": "upper critical",
                    "Severity": 1,
                    "Value": 95
                }
            ],
            "Type": "XeonCPU"
        },        
        {
            "Index": 0,
            "Name": "VOL_SYS_12V",
            "PowerState": "On",
            "ScaleFactor": 0.1124,
            "MaxReading": 18,
            "Thresholds": [
                {
                    "Direction": "greater than",
                    "Name": "upper critical",
                    "Severity": 1,
                    "Value": 13.140
                },
                {
                    "Direction": "less than",
                    "Name": "lower critical",
                    "Severity": 1,
                    "Value": 10.800
                }
            ],
            "Type": "ADC"
        },
        {
            "Index": 1,
            "Name": "VOL_SYS_3V3",
            "PowerState": "On",
            "ScaleFactor": 0.411,
            "MaxReading": 5,
            "Thresholds": [
                {
                    "Direction": "greater than",
                    "Name": "upper critical",
                    "Severity": 1,
                    "Value": 3.564
                },
                {
                    "Direction": "less than",
                    "Name": "lower critical",
                    "Severity": 1,
                    "Value": 3.036
                }
            ],
            "Type": "ADC"
        },
        {
            "Index": 2,
            "Name": "VOL_PCH_VNN_AUX",
            "PowerState": "Always",
            "ScaleFactor": 1,
            "MaxReading": 2,
            "Thresholds": [
                {
                    "Direction": "greater than",
                    "Name": "upper critical",
                    "Severity": 1,
                    "Value": 1.076
                },
                {
                    "Direction": "less than",
                    "Name": "lower critical",
                    "Severity": 1,
                    "Value": 0.819
                }
            ],
            "Type": "ADC"
        },
        {
            "Index": 3,
            "Name": "VOL_PCH_1V05_AUX",
            "PowerState": "Always",
            "ScaleFactor": 1,
            "MaxReading": 2,
            "Thresholds": [
                {
                    "Direction": "greater than",
                    "Name": "upper critical",
                    "Severity": 1,
                    "Value": 1.115
                },
                {
                    "Direction": "less than",
                    "Name": "lower critical",
                    "Severity": 1,
                    "Value": 0.983
                }
            ],
            "Type": "ADC"
        },
        {
            "Index": 4,
            "Name": "VOL_3V3_AUX",
            "PowerState": "Always",
            "ScaleFactor": 0.411,
            "MaxReading": 5,
            "Thresholds": [
                {
                    "Direction": "greater than",
                    "Name": "upper critical",
                    "Severity": 1,
                    "Value": 3.564
                },
                {
                    "Direction": "less than",
                    "Name": "lower critical",
                    "Severity": 1,
                    "Value": 3.036
                }
            ],
            "Type": "ADC"
        },
        {
            "Index": 5,
            "Name": "VOL_5V_AUX",
            "PowerState": "Always",
            "ScaleFactor": 0.272,
            "MaxReading": 10,
            "Thresholds": [
                {
                    "Direction": "greater than",
                    "Name": "upper critical",
                    "Severity": 1,
                    "Value": 5.400
                },
                {
                    "Direction": "less than",
                    "Name": "lower critical",
                    "Severity": 1,
                    "Value": 4.600
                }
            ],
            "Type": "ADC"
        },
        {
            "Index": 6,
            "Name": "VOL_PCH_1V8_AUX",
            "PowerState": "Always",
            "ScaleFactor": 0.750,
            "MaxReading": 3,
            "Thresholds": [
                {
                    "Direction": "greater than",
                    "Name": "upper critical",
                    "Severity": 1,
                    "Value": 1.935
                },
                {
                    "Direction": "less than",
                    "Name": "lower critical",
                    "Severity": 1,
                    "Value": 1.674
                }
            ],
            "Type": "ADC"
        },
        {
            "BridgeGpio": [
                {
                    "Name": "BAT_MON",
                    "Polarity": "High"
                }
            ],
            "Index": 7,
            "Name": "VOL_BATTERY",
            "PowerState": "Always",
            "ScaleFactor": 0.3333,
            "MaxReading": 5,
            "Thresholds": [
                {
                    "Direction": "greater than",
                    "Name": "upper critical",
                    "Severity": 1,
                    "Value": 3.482
                },
                {
                    "Direction": "less than",
                    "Name": "lower critical",
                    "Severity": 1,
                    "Value": 2.702
                }
            ],
            "Type": "ADC"
        },
        {
            "Index": 8,
            "Name": "VOL_CPU0_VCORE",
            "PowerState": "On",
            "ScaleFactor": 0.742,
            "MaxReading": 3,
            "Thresholds": [
                {
                    "Direction": "greater than",
                    "Name": "upper critical",
                    "Severity": 1,
                    "Value": 2.065
                },
                {
                    "Direction": "less than",
                    "Name": "lower critical",
                    "Severity": 1,
                    "Value": 1.440
                }
            ],
            "Type": "ADC"
        },
        {
            "Index": 9,
            "Name": "VOL_SYS_5V",
            "PowerState": "On",
            "ScaleFactor": 0.272,
            "MaxReading": 10,
            "Thresholds": [
                {
                    "Direction": "greater than",
                    "Name": "upper critical",
                    "Severity": 1,
                    "Value": 5.400
                },
                {
                    "Direction": "less than",
                    "Name": "lower critical",
                    "Severity": 1,
                    "Value": 4.600
                }
            ],
            "Type": "ADC"
        },
        {
            "Index": 10,
            "Name": "VOL_DIMM_ABC",
            "PowerState": "On",
            "ScaleFactor": 1,
            "MaxReading": 2,
            "Thresholds": [
                {
                    "Direction": "greater than",
                    "Name": "upper critical",
                    "Severity": 1,
                    "Value": 1.349
                },
                {
                    "Direction": "less than",
                    "Name": "lower critical",
                    "Severity": 1,
                    "Value": 1.100
                }
            ],
            "Type": "ADC"
        },
        {
            "Index": 11,
            "Name": "VOL_DIMM_DEF",
            "PowerState": "On",
            "ScaleFactor": 1,
            "MaxReading": 2,
            "Thresholds": [
                {
                    "Direction": "greater than",
                    "Name": "upper critical",
                    "Severity": 1,
                    "Value": 1.349
                },
                {
                    "Direction": "less than",
                    "Name": "lower critical",
                    "Severity": 1,
                    "Value": 1.100
                }
            ],
            "Type": "ADC"
        },
        {
            "Index": 14,
            "Name": "VOL_SYS0_VCCIO",
            "PowerState": "On",
            "ScaleFactor": 1,
            "MaxReading": 2,
            "Thresholds": [
                {
                    "Direction": "greater than",
                    "Name": "upper critical",
                    "Severity": 1,
                    "Value": 1.139
                },
                {
                    "Direction": "less than",
                    "Name": "lower critical",
                    "Severity": 1,
                    "Value": 0.772
                }
            ],
            "Type": "ADC"
        },
        {

            "Connector": {
                "Name": "CPU Fan Connector 0",
                "Pwm": 0,
                "Tachs": [
                    0
                ]
            },
            "Index": 0,
            "Name": "CPU_FAN_0",
            "Thresholds": [
                {
                    "Direction": "less than",
                    "Name": "lower critical",
                    "Severity": 1,
                    "Value": 100
                }
            ],
            "Type": "AspeedFan"
        },
        {
            "Connector": {
                "Name": "CPU Fan Connector 1",
                "Pwm": 1,
                "Tachs": [
                    1
                ]
            },
            "Index": 1,
            "Name": "SYS_FAN_0",
            "Thresholds": [
                {
                    "Direction": "less than",
                    "Name": "lower critical",
                    "Severity": 1,
                    "Value": 100
                }
            ],
            "Type": "AspeedFan"
        },
        {
            "Connector": {
                "Name": "Sys FAN Connector 0",
                "Pwm": 2,
                "Tachs": [
                    2
                ]
            },
            "Index": 2,
            "Name": "SYS_FAN_1",
            "Thresholds": [
                {
                    "Direction": "less than",
                    "Name": "lower critical",
                    "Severity": 1,
                    "Value": 100
                }
            ],
            "Type": "AspeedFan"
        },
        {
            "Connector": {
                "Name": "Sys FAN Connector 1",
                "Pwm": 3,
                "Tachs": [
                    3
                ]
            },
            "Index": 3,
            "Name": "SYS_FAN_2",
            "Thresholds": [
                {
                    "Direction": "less than",
                    "Name": "lower critical",
                    "Severity": 1,
                    "Value": 100
                }
            ],
            "Type": "AspeedFan"
        },
        {
            "Connector": {
                "Name": "Sys FAN Connector 2",
                "Pwm": 4,
                "Tachs": [
                    4
                ]
            },
            "Index": 4,
            "Name": "SYS_FAN_3",
            "Thresholds": [
                {
                    "Direction": "less than",
                    "Name": "lower critical",
                    "Severity": 1,
                    "Value": 100
                }
            ],
            "Type": "AspeedFan"
        },
        {
            "Connector": {
                "Name": "Sys FAN Connector 2",
                "Pwm": 5,
                "Tachs": [
                    5
                ]
            },
            "Index": 5,
            "Name": "SYS_FAN_4",
            "Thresholds": [
                {
                    "Direction": "less than",
                    "Name": "lower critical",
                    "Severity": 1,
                    "Value": 100
                }
            ],
            "Type": "AspeedFan"
        },
        {
            "Address": "0x49",
            "Bus": 6,
            "Name": "SYS_Air_Inlet",
            "HysteresisVal": 3,
            "Thresholds": [
                {
                    "Direction": "greater than",
                    "Label": "temp1",
                    "Name": "upper critical",
                    "Severity": 1,
                    "Value": 70
                }
            ],
            "Type": "TMP75"
        },
        {
            "Address": "0x4a",
            "Bus": 6,
            "Name": "SYS_Air_Outlet",
            "HysteresisVal": 3,
            "Thresholds": [
                {
                    "Direction": "greater than",
                    "Label": "temp1",
                    "Name": "upper critical",
                    "Severity": 1,
                    "Value": 70
                }
            ],
            "Type": "TMP75"
        },
        {
            "Address": "0x58",
            "Bus": 10,
            "Reg": "0x8d",
            "Class": "MOSTempLinear",
            "Name": "CPU0_MOS",
            "Thresholds": [
                {
                    "Direction": "greater than",
                    "Name": "upper critical",
                    "Severity": 1,
                    "Value": 110
                }
            ],
            "Type": "MOSTempSensor"
        },
        {
            "Address": "0x68",
            "Bus": 10,
            "Reg": "0x8d",
            "Class": "MOSTempLinear",
            "Name": "CPU0_DIMM_MOS_1",
            "Thresholds": [
                {
                    "Direction": "greater than",
                    "Name": "upper critical",
                    "Severity": 1,
                    "Value": 110
                }
            ],
            "Type": "MOSTempSensor"
        },
        {
            "Address": "0x6A",
            "Bus": 10,
            "Reg": "0x8d",
            "Class": "MOSTempLinear",
            "Name": "CPU0_DIMM_MOS_2",
            "Thresholds": [
                {
                    "Direction": "greater than",
                    "Name": "upper critical",
                    "Severity": 1,
                    "Value": 110
                }
            ],
            "Type": "MOSTempSensor"
        },
        {
            "FailSafePercent": 25,
            "MinThermalOutput": 25,
            "CommandSet": 0,
            "FloorDuty": 0,
            "Name": "Pid 1",
            "Type": "Pid.Zone"
        },
        {
            "FailSafePercent": 25,
            "MinThermalOutput": 25,
            "CommandSet": 0,
            "FloorDuty": 0,
            "Name": "Pid 2",
            "Type": "Pid.Zone"
        },
        {
            "FailSafePercent": 25,
            "MinThermalOutput": 25,
            "CommandSet": 0,
            "FloorDuty": 0,
            "Name": "Pid 3",
            "Type": "Pid.Zone"
        },
        {
            "FailSafePercent": 25,
            "MinThermalOutput": 25,
            "CommandSet": 0,
            "FloorDuty": 0,
            "Name": "Pid 4",
            "Type": "Pid.Zone"
        },
        {
            "FailSafePercent": 25,
            "MinThermalOutput": 25,
            "CommandSet": 0,
            "FloorDuty": 0,
            "Name": "Pid 5",
            "Type": "Pid.Zone"
        },
        {
            "FailSafePercent": 25,
            "MinThermalOutput": 25,
            "CommandSet": 0,
            "FloorDuty": 0,
            "Name": "Pid 6",
            "Type": "Pid.Zone"
        },
        {
            "Class": "temp",
            "Inputs": [
                "SYS_Air_Inlet"
            ],
            "Name": "FSC_CPU0",
            "SetPointH": 5000,
            "SetPointL": 10000,
            "OutLimitMax": 70,
            "NegativeHysteresis": 0,
            "Output": [
                25.0,
                30.0
            ],
            "PositiveHysteresis": 0,
            "Reading": [
                29.0,
                30.0
            ],
            "Type": "Fsc",
            "Zones": [
                "Pid 1",
                "Pid 2",
                "Pid 3",
                "Pid 4",
                "Pid 5",
                "Pid 6"
            ]
        },
        {
            "Class": "fan",
            "FFGainCoefficient": 1.0,
            "FFOffCoefficient": 0.0,
            "ICoefficient": 0.0,
            "ILimitMax": 0.0,
            "ILimitMin": 0.0,
            "Inputs": [
                "CPU_FAN_0"
            ],
            "Name": "FSC_SYS_FAN_1",
            "OutLimitMax": 100.0,
            "OutLimitMin": 25.0,
            "Outputs": [
                "Pwm 1"
            ],
            "PCoefficient": 0.0,
            "SlewNeg": 0.0,
            "SlewPos": 0.0,
            "Type": "Pid",
            "Zones": [
                "Pid 1"
            ]
        },
        {
            "Class": "fan",
            "FFGainCoefficient": 1.0,
            "FFOffCoefficient": 0.0,
            "ICoefficient": 0.0,
            "ILimitMax": 0.0,
            "ILimitMin": 0.0,
            "Inputs": [
                "SYS_FAN_0"
            ],
            "Name": "FSC_SYS_FAN_2",
            "OutLimitMax": 100.0,
            "OutLimitMin": 25.0,
            "Outputs": [
                "Pwm 2"
            ],
            "PCoefficient": 0.0,
            "SlewNeg": 0.0,
            "SlewPos": 0.0,
            "Type": "Pid",
            "Zones": [
                "Pid 2"
            ]
        },
        {
            "Class": "fan",
            "FFGainCoefficient": 1.0,
            "FFOffCoefficient": 0.0,
            "ICoefficient": 0.0,
            "ILimitMax": 0.0,
            "ILimitMin": 0.0,
            "Inputs": [
                "SYS_FAN_1"
            ],
            "Name": "FSC_SYS_FAN_3",
            "OutLimitMax": 100.0,
            "OutLimitMin": 25.0,
            "Outputs": [
                "Pwm 3"
            ],
            "PCoefficient": 0.0,
            "SlewNeg": 0.0,
            "SlewPos": 0.0,
            "Type": "Pid",
            "Zones": [
                "Pid 3"
            ]
        },
        {
            "Class": "fan",
            "FFGainCoefficient": 1.0,
            "FFOffCoefficient": 0.0,
            "ICoefficient": 0.0,
            "ILimitMax": 0.0,
            "ILimitMin": 0.0,
            "Inputs": [
                "SYS_FAN_2"
            ],
            "Name": "FSC_SYS_FAN_4",
            "OutLimitMax": 100.0,
            "OutLimitMin": 25.0,
            "Outputs": [
                "Pwm 4"
            ],
            "PCoefficient": 0.0,
            "SlewNeg": 0.0,
            "SlewPos": 0.0,
            "Type": "Pid",
            "Zones": [
                "Pid 4"
            ]
        },
        {
            "Class": "fan",
            "FFGainCoefficient": 1.0,
            "FFOffCoefficient": 0.0,
            "ICoefficient": 0.0,
            "ILimitMax": 0.0,
            "ILimitMin": 0.0,
            "Inputs": [
                "SYS_FAN_3"
            ],
            "Name": "FSC_SYS_FAN_5",
            "OutLimitMax": 100.0,
            "OutLimitMin": 25.0,
            "Outputs": [
                "Pwm 5"
            ],
            "PCoefficient": 0.0,
            "SlewNeg": 0.0,
            "SlewPos": 0.0,
            "Type": "Pid",
            "Zones": [
                "Pid 5"
            ]
        },
        {
            "Class": "fan",
            "FFGainCoefficient": 1.0,
            "FFOffCoefficient": 0.0,
            "ICoefficient": 0.0,
            "ILimitMax": 0.0,
            "ILimitMin": 0.0,
            "Inputs": [
                "SYS_FAN_4"
            ],
            "Name": "FSC_SYS_FAN_6",
            "OutLimitMax": 100.0,
            "OutLimitMin": 25.0,
            "Outputs": [
                "Pwm 6"
            ],
            "PCoefficient": 0.0,
            "SlewNeg": 0.0,
            "SlewPos": 0.0,
            "Type": "Pid",
            "Zones": [
                "Pid 6"
            ]
        }
    ],
    "Name": "s5549 Baseboard",
    "Probe": "xyz.openbmc_project.FruDevice({'BOARD_PRODUCT_NAME': '.*E3331*'})",
    "Type": "Board",
    "xyz.openbmc_project.Inventory.Decorator.Asset": {
        "ChassisType": "$CHASSIS_TYPE",
        "ChassisPartNumber": "$CHASSIS_PART_NUMBER",
        "ChassisSerial": "$CHASSIS_SERIAL_NUMBER",
        "ChassisExtra": "$CHASSIS_INFO_AM1",
        "BoardMfgDate": "$BOARD_MANUFACTURE_DATE",
        "BoardMfg": "$BOARD_MANUFACTURER",
        "BoardProduct": "$BOARD_PRODUCT_NAME",
        "BoardSerial": "$BOARD_SERIAL_NUMBER",
        "BoardPartNumber": "$BOARD_PRODUCT_NAME",
        "ProductName": "$PRODUCT_PRODUCT_NAME",
        "ProductPartNumber": "$PRODUCT_PART_NUMBER",
        "ProductVersion": "$PRODUCT_VERSION",
        "ProductSerial": "$PRODUCT_SERIAL_NUMBER"
    }
}
